py_wifi_geter/__init__.py
py_wifi_geter/main.py
py_wifi_geter-0.1.1.dist-info/LICENSE
py_wifi_geter-0.1.1.dist-info/METADATA
py_wifi_geter-0.1.1.dist-info/WHEEL
py_wifi_geter-0.1.1.dist-info/top_level.txt
py_wifi_geter-0.1.1.dist-info/RECORD
