Metadata-Version: 2.1
Name: py-wifi-geter
Version: 0.1.1
License-File: LICENSE
Requires-Dist: requests
